[
    {
        "manufacturer": "Oppo",
        "model": "3000"
    },
    {
        "manufacturer": "Oppo",
        "model": "Find 5"
    },
    {
        "manufacturer": "Oppo",
        "model": "Find 7"
    },
    {
        "manufacturer": "Oppo",
        "model": "Find 7a"
    },
    {
        "manufacturer": "Oppo",
        "model": "N1"
    },
    {
        "manufacturer": "Oppo",
        "model": "N3"
    },
    {
        "manufacturer": "Oppo",
        "model": "R1C"
    },
    {
        "manufacturer": "Oppo",
        "model": "R1L"
    },
    {
        "manufacturer": "Oppo",
        "model": "R1S"
    },
    {
        "manufacturer": "Oppo",
        "model": "U3"
    }
]